django_moo_url/__init__.py
django_moo_url/main.py
django_moo_url-1.2.2.dist-info/METADATA
django_moo_url-1.2.2.dist-info/WHEEL
django_moo_url-1.2.2.dist-info/license
django_moo_url-1.2.2.dist-info/top_level.txt
django_moo_url-1.2.2.dist-info/RECORD
