Metadata-Version: 2.1
Name: django-moo-url
Version: 1.2.2
Summary: the simplest django view decorator.
Home-page: https://gitee.com/nerd-mo/django_url
Author: Monacede Lee
Author-email: 1904981400@qq.com
License: MIT
Platform: UNKNOWN
Classifier: License :: OSI Approved :: MIT License
Classifier: Programming Language :: Python
Classifier: Programming Language :: Python :: 3
Classifier: Programming Language :: Python :: 3.6
Classifier: Programming Language :: Python :: Implementation :: CPython
Classifier: Programming Language :: Python :: Implementation :: PyPy
Requires-Python: >=3.6.0
Requires-Dist: django
